pandasai_bigquery/__init__.py
pandasai_bigquery-0.1.4.dist-info/LICENSE
pandasai_bigquery-0.1.4.dist-info/METADATA
pandasai_bigquery-0.1.4.dist-info/WHEEL
pandasai_bigquery-0.1.4.dist-info/RECORD
